{
  "_class": "text",
  "attributedString": {
    "_class": "attributedString",
    "attributes": [
      {
        "_class": "stringAttribute",
        "attributes": {
          "MSAttributedStringColorAttribute": {
            "_class": "color",
            "alpha": 1,
            "blue": 1,
            "green": 1,
            "red": 1
          },
          "MSAttributedStringFontAttribute": {
            "_class": "fontDescriptor",
            "attributes": {
              "name": "Verdana-Bold",
              "size": 16
            }
          },
          "kerning": 0,
          "paragraphStyle": {
            "_class": "paragraphStyle",
            "alignment": 2,
            "maximumLineHeight": 21,
            "minimumLineHeight": 21,
            "paragraphSpacing": 12
          },
          "strikethroughStyle": 0,
          "textStyleVerticalAlignmentKey": 0,
          "underlineStyle": 0
        },
        "length": 15,
        "location": 0
      }
    ],
    "string": "content filters"
  },
  "automaticallyDrawOnUnderlyingPath": false,
  "booleanOperation": -1,
  "clippingMaskMode": 0,
  "do_objectID": "D23C50C6-A07A-4FC1-9CA3-45C53B50A6C2",
  "dontSynchroniseWithSymbol": false,
  "exportOptions": {
    "_class": "exportOptions",
    "do_objectID": "FAEACC5E-F409-458A-B9F5-9E2699722DBD",
    "exportFormats": [
    ],
    "includedLayerIds": [
    ],
    "layerOptions": 0,
    "shouldTrim": false
  },
  "frame": {
    "_class": "rect",
    "constrainProportions": false,
    "do_objectID": "5484E558-5CB6-4923-A744-03BD6FD90769",
    "height": 21,
    "width": 127,
    "x": 572,
    "y": 111
  },
  "glyphBounds": "{{0, 4}, {127, 14}}",
  "hasClippingMask": false,
  "isFixedToViewport": false,
  "isFlippedHorizontal": false,
  "isFlippedVertical": false,
  "isLocked": false,
  "isVisible": true,
  "layerListExpandedType": 0,
  "lineSpacingBehaviour": 2,
  "name": "content filters",
  "nameIsFixed": false,
  "resizingConstraint": 47,
  "resizingType": 0,
  "rotation": 0,
  "sharedStyleID": "E6811DA5-51A0-4BF6-9012-13B40721086F",
  "shouldBreakMaskChain": false,
  "style": {
    "_class": "style",
    "do_objectID": "75F56C43-3938-4109-B910-87760480F44F",
    "endMarkerType": 0,
    "miterLimit": 10,
    "startMarkerType": 0,
    "textStyle": {
      "_class": "textStyle",
      "do_objectID": "B5549D47-3158-48EC-96F3-AE43861AFCD2",
      "encodedAttributes": {
        "MSAttributedStringColorAttribute": {
          "_class": "color",
          "alpha": 1,
          "blue": 1,
          "green": 1,
          "red": 1
        },
        "MSAttributedStringFontAttribute": {
          "_class": "fontDescriptor",
          "attributes": {
            "name": "Verdana-Bold",
            "size": 16
          }
        },
        "kerning": 0,
        "paragraphStyle": {
          "_class": "paragraphStyle",
          "alignment": 2,
          "maximumLineHeight": 21,
          "minimumLineHeight": 21,
          "paragraphSpacing": 12
        },
        "strikethroughStyle": 0,
        "textStyleVerticalAlignmentKey": 0,
        "underlineStyle": 0
      },
      "verticalAlignment": 0
    },
    "windingRule": 1
  },
  "textBehaviour": 0
}